---
layout: post
title:  "Java Core 3 foreach 和可变参数列表"
date:   "2016-02-14 17:50:00"
categories: java
keywords: java
---


1. foreach 的实现原理

foreach 要求数组或java.lang.Iterable

看下jdk源码对Iterable接口的声明：

```java
/** Implementing this interface allows an object to be the target of
 *  the "foreach" statement.
 * @since 1.5
 */
public interface Iterable<T> {

    /**
     * Returns an iterator over a set of elements of type T.
     * 
     * @return an Iterator.
     */
    Iterator<T> iterator();
}
```

实现此接口，允许成为foreach语法的target。

那数组呢？数组没有实现为什么也可以用呢？

那是因为遍历数组时，会转换为对数组中的每一个元素的循环引用，相当于for语法循环遍历一样。

那么为什么是数组或者实现了这个接口，就能实现遍历呢？其实是因为编译器的原因，在编译中的语义分析过程中，有一个解除语法糖的操作，（语法糖是啥？可以理解成编译器为方便开发人员开发，会对特定代码做一些特殊处理，方便开发人员使用，除了foreach，java中还有泛型、装箱、拆箱、变长字符串等）。

1. 对于list编译器会调用Iterable接口的 iterator方法来循环遍历数组的元素，iterator方法中是调用Iterator接口的的 next()和hasNext（）方法来做循环遍历。java中有一个叫做迭代器模式的设计模式，这个其实就是对迭代器模式的一个实现。
2. 对于数组，就是转化为对数组中的每一个元素的循环引用

```java
public static void main(String[] args) {
    List<String> list = new ArrayList<String>();
    list.add("111");
    list.add("222");
    
    for (String str : list) {
        System.out.println(str);
    }
}

 1   public static void main(java.lang.String[]);
 2     flags: ACC_PUBLIC, ACC_STATIC
 3     Code:
 4       stack=2, locals=4, args_size=1
 5          0: new           #16                 // class java/util/ArrayList
 6          3: dup
 7          4: invokespecial #18                 // Method java/util/ArrayList."<init>":()V
 9          7: astore_1
10          8: aload_1
11          9: ldc           #19                 // String 111
12         11: invokeinterface #21,  2           // InterfaceMethod java/util/List.add:(Ljava/lang/Object;)Z
14         16: pop
15         17: aload_1
16         18: ldc           #27                 // String 222
17         20: invokeinterface #21,  2           // InterfaceMethod java/util/List.add:(Ljava/lang/Object;)Z
19         25: pop
20         26: aload_1
21         27: invokeinterface #29,  1           // InterfaceMethod java/util/List.iterator:()Ljava/util/Iterator;
```

看不懂没关系，new、dup、invokespecial这些本来就是字节码指令表内定义的指令，虚拟机会根据这些指令去执行指定的C++代码，完成每个指令的功能。关键看到21、22这两行就可以了，看到了一个iterator，所以得出结论：在编译的时候编译器会自动将对for这个关键字的使用转化为对目标的迭代器的使用，这就是foreach循环的原理。进而，我们再得出两个结论：

1. ArrayList之所以能使用foreach循环遍历，是因为ArrayList所有的List都是Collection的子接口，而Collection是Iterable的子接口，ArrayList的父类AbstractList正确地实现了Iterable接口的iterator方法。之前我自己写的ArrayList用foreach循环直接报空指针异常是因为我自己写的ArrayList并没有实现Iterable接口

2. 任何一个集合，无论是JDK提供的还是自己写的，只要想使用foreach循环遍历，就必须正确地实现Iterable接口



2. 可变长度参数

```java
public static void main(String[] args) {
    print("000", "111", "222", "333");
}
    
public static void print(String... strs) {
    for (int i = 0; i < strs.length; i++) {
        System.out.println(strs[i]);
    }
}
```

最后，注意一点，可变长度参数必须作为方法参数列表中的的最后一个参数且方法参数列表中只能有一个可变长度参数。


